odoo8_addon_project_issue_department-8.0.1.1.0.99.dev3-py2.7-nspkg.pth
odoo8_addon_project_issue_department-8.0.1.1.0.99.dev3.dist-info/METADATA
odoo8_addon_project_issue_department-8.0.1.1.0.99.dev3.dist-info/RECORD
odoo8_addon_project_issue_department-8.0.1.1.0.99.dev3.dist-info/WHEEL
odoo8_addon_project_issue_department-8.0.1.1.0.99.dev3.dist-info/namespace_packages.txt
odoo8_addon_project_issue_department-8.0.1.1.0.99.dev3.dist-info/top_level.txt
odoo_addons/project_issue_department/__init__.py
odoo_addons/project_issue_department/__openerp__.py
odoo_addons/project_issue_department/project_issue.py
odoo_addons/project_issue_department/project_issue_view.xml
odoo_addons/project_issue_department/security/ir.model.access.csv
odoo_addons/project_issue_department/static/description/icon.png
