Metadata-Version: 2.1
Name: odoo8-addon-project-issue-department
Version: 8.0.1.1.0.99.dev3
Summary: Project Issue with Department
Home-page: https://odoo-community.org
Author: Daniel Reis,Odoo Community Association (OCA)
Author-email: support@odoo-community.org
License: AGPL-3
Platform: UNKNOWN
Classifier: Programming Language :: Python
Classifier: Framework :: Odoo
Classifier: License :: OSI Approved :: GNU Affero General Public License v3
Requires-Python: ~=2.7
Requires-Dist: odoo8-addon-project-department
Requires-Dist: odoo (<9.0a,>=8.0a)
